log/__init__.py
log/log.py
mylog-0.0.1.dist-info/METADATA
mylog-0.0.1.dist-info/WHEEL
mylog-0.0.1.dist-info/top_level.txt
mylog-0.0.1.dist-info/RECORD
