Metadata-Version: 2.1
Name: mylog
Version: 0.0.1
Summary: colored log for python
Home-page: UNKNOWN
Author: j2
License: UNKNOWN
Platform: UNKNOWN
Classifier: Programming Language :: Python :: 3
Classifier: Operating System :: OS Independent
Requires-Python: >=3
